gherlint/__init__.py
gherlint/__main__.py
gherlint/checkers/__init__.py
gherlint/checkers/base_checker.py
gherlint/checkers/completeness.py
gherlint/checkers/complexity.py
gherlint/checkers/consistency.py
gherlint/exceptions.py
gherlint/fixer.py
gherlint/linter.py
gherlint/objectmodel/__init__.py
gherlint/objectmodel/nodes.py
gherlint/parser.py
gherlint/registry.py
gherlint/reporting.py
gherlint/statistics.py
gherlint/utils.py
gherlint/walker.py
gherlint-0.4.0.dist-info/entry_points.txt
gherlint-0.4.0.dist-info/LICENSE
gherlint-0.4.0.dist-info/WHEEL
gherlint-0.4.0.dist-info/METADATA
gherlint-0.4.0.dist-info/RECORD
