Metadata-Version: 2.1
Name: gherlint
Version: 0.4.0
Summary: Linter for Gherkin feature files
Home-page: https://github.com/DudeNr33/gherlint
License: MIT
Keywords: gherkin,cucumber,lint,static analysis,internal quality
Author: Andreas Finkler
Requires-Python: >=3.8,<4.0
Classifier: Development Status :: 3 - Alpha
Classifier: License :: OSI Approved :: MIT License
Classifier: Programming Language :: Python :: 3
Classifier: Programming Language :: Python :: 3.10
Classifier: Programming Language :: Python :: 3.8
Classifier: Programming Language :: Python :: 3.9
Classifier: Topic :: Software Development
Classifier: Topic :: Software Development :: Quality Assurance
Classifier: Topic :: Software Development :: Testing
Requires-Dist: click (>=8.0.1,<9.0.0)
Requires-Dist: gherkin-official (>=22.0.0,<23.0.0)
Requires-Dist: parse (>=1.19.0,<2.0.0)
